bit_permutation/__init__.py
bit_permutation/constants.py
bit_permutation/permutation.py
bit_permutation/shuffle.py
bit_permutation/xor.py
bit_permutation-1.0.22.dist-info/licenses/LICENSE
bit_permutation-1.0.22.dist-info/WHEEL
bit_permutation-1.0.22.dist-info/METADATA
bit_permutation-1.0.22.dist-info/RECORD
