Metadata-Version: 2.4
Name: bit-permutation
Version: 1.0.22
Summary: Shuffle bits in integer numbers
Author-email: Oleh Alistratov <alistratov.dev@gmail.com>
Requires-Python: >=3.10
Classifier: Development Status :: 5 - Production/Stable
Classifier: Programming Language :: Python :: 3
Classifier: License :: OSI Approved :: Apache Software License
Classifier: Operating System :: OS Independent
License-File: LICENSE
Project-URL: Documentation, https://bit-permutation.alistratov.name/en/latest/
Project-URL: Homepage, https://github.com/alistratov/bit-permutation
Project-URL: Issues, https://github.com/alistratov/bit-permutation/issues
